h264/updates/coretransform/h264coretransform_controller.sv
module h264coretransform_controller(
    input logic CLK,                    // Clock Signal
    input logic RESET,                  // Reset Signal to reset state machine
    input logic ENABLE,                 // Enable signal for state machine
    input logic input_1,                // Input signal for FSM-1 // Pipeline 2-5
    output logic en_pipeline2,en_pipeline3,en_pipeline4,en_pipeline5
);


// For FSM-1 - Moore Machine with 8 states; S0,S1,S2,S3,S4,S5,S6,S7
// FSM-1 - To control Pipeline 2-5
logic [2:0] c_state1, n_state1;
//logic input_1;
parameter S0 = 3'b000, S1=3'b001, S2=3'b010, S3=3'b011, S4=3'b100, S5=3'b101, S6= 3'b110, S7 = 3'b111;

//FSM-1 State Logic
always_comb
begin
    // Next State Logic
    //input_1 = (ixx != 0); // Input signal to progress states
    case (c_state1)
        S0: begin 
                if (ENABLE) 
                    n_state1 = S1;
            end
        S1: n_state1 = S2;
        S2: n_state1 = S3;
        S3: n_state1 = S4;
        S4: n_state1 = S5;
        S5: n_state1 = S6;
        S6: n_state1 = S7;
        S7: n_state1 = S0;
        default: n_state1 = S0;
    endcase

    // Current State Logic
    case (c_state1)
    S0: begin // Clear all signals
            en_pipeline2 = 1'b0;
            en_pipeline3 = 1'b0;
            en_pipeline4 = 1'b0;
            en_pipeline5 = 1'b0;
        end
    S1: begin // Set en_pipeline2
            en_pipeline2 = 1'b1;
            en_pipeline3 = 1'b0;
            en_pipeline4 = 1'b0;
            en_pipeline5 = 1'b0;
        end
    S2: begin // Set en_pipeline2, en_pipeline3
            en_pipeline2 = 1'b1;
            en_pipeline3 = 1'b1;
            en_pipeline4 = 1'b0;
            en_pipeline5 = 1'b0;
        end
    S3: begin // Set en_pipeline2, en_pipeline4
            en_pipeline2 = 1'b1;
            en_pipeline3 = 1'b0;
            en_pipeline4 = 1'b1;
            en_pipeline5 = 1'b0;
        end
    S4: begin // Set en_pipeline2, en)en_pipeline5
            en_pipeline2 = 1'b1;
            en_pipeline3 = 1'b0;
            en_pipeline4 = 1'b0;
            en_pipeline5 = 1'b1;
        end
    S5: begin // Clear all signals
            en_pipeline2 = 1'b0;
            en_pipeline3 = 1'b0;
            en_pipeline4 = 1'b0;
            en_pipeline5 = 1'b0;
        end
    S6: begin // Clear all signals
            en_pipeline2 = 1'b0;
            en_pipeline3 = 1'b0;
            en_pipeline4 = 1'b0;
            en_pipeline5 = 1'b0;
        end
    S7: begin // Clear all signals
            en_pipeline2 = 1'b0;
            en_pipeline3 = 1'b0;
            en_pipeline4 = 1'b0;
            en_pipeline5 = 1'b0;
        end
    default: begin // Clear all signals
            en_pipeline2 = 1'b0;
            en_pipeline3 = 1'b0;
            en_pipeline4 = 1'b0;
            en_pipeline5 = 1'b0;
        end
    endcase // End of FSM-1
end

// FSM-1 State Transition
always_ff @(posedge CLK)
begin
    // FSM-1 : Moore Machine with 8 States; S0,S1,S2,S3,S4,S5,S6,S7

    //reset is active low
    if (!RESET)
        c_state1 <= S0;        // IDLE State
    else
        c_state1 <= n_state1;   // Next State
    // Rest of the FSM-1 is in always_comb block
end

endmodule

h264/updates/coretransform/h264coretransform.sv

// H264 - Core Transform

module h264coretransform
(
    input logic CLK,	// fast io clock
    input logic RESET,
    output logic READY = '0,		//set when ready for ENABLE
    input logic ENABLE,				//values input only when this is 1
    input logic [35:0] XXIN,	 //4 x 9bit, first px is lsbs
    output logic VALID = '0,				//values output only when this is 1
    output logic [13:0] YNOUT = '0	//output (zigzag order)
);



logic [1:0] yny, ynx;
logic [8:0]  xx0, xx1, xx2, xx3;


assign xx0 = XXIN[8:0];
assign xx1 = XXIN[17:9];
assign xx2 = XXIN[26:18];
assign xx3 = XXIN[35:27];

logic [9:0] xt0 = 10'd0;
logic [9:0] xt1 = 10'd0;
logic [9:0] xt2 = 10'd0;
logic [9:0] xt3 = 10'd0;

logic [11:0] ff00 = 12'd0;
logic [11:0] ff01 = 12'd0;
logic [11:0] ff02 = 12'd0;
logic [11:0] ff03 = 12'd0;
logic [11:0] ff10 = 12'd0;
logic [11:0] ff11 = 12'd0;
logic [11:0] ff12 = 12'd0;
logic [11:0] ff13 = 12'd0;
logic [11:0] ff20 = 12'd0;
logic [11:0] ff21 = 12'd0;
logic [11:0] ff22 = 12'd0;
logic [11:0] ff23 = 12'd0;
logic [11:0] ffx0 = 12'd0;
logic [11:0] ffx1 = 12'd0;
logic [11:0] ffx2 = 12'd0;
logic [11:0] ffx3 = 12'd0;
logic [11:0] ff0p = 12'd0;
logic [11:0] ff1p = 12'd0;
logic [11:0] ff2p = 12'd0;
logic [11:0] ff3p = 12'd0;
logic [11:0] ff0pu = 12'd0;
logic [11:0] ff1pu = 12'd0;
logic [11:0] ff2pu = 12'd0;
logic [11:0] ff3pu = 12'd0;
logic [12:0] yt0 = 13'd0;
logic [12:0] yt1 = 13'd0;
logic [12:0] yt2 = 13'd0;
logic [12:0] yt3 = 13'd0;
logic valid1 = 1'd0;
logic valid2 = 1'd0;

logic [2:0] ixx = 3'd0;
logic [3:0] iyn = 4'd0;

logic [3:0] ynyx = 4'd0;

logic [1:0] yny1 = 2'd0;
logic [1:0] yny2 = 2'd0;

localparam ROW0 = 2'b00;
localparam ROW1 = 2'b01;
localparam ROW2 = 2'b10;
localparam ROW3 = 2'b11;
localparam COL0 = 2'b00;
localparam COL1 = 2'b01;
localparam COL2 = 2'b10;
localparam COL3 = 2'b11;

assign yny = ynyx[3:2];
assign ynx = ynyx [1:0];

// New Parameters

logic input_1;  // Input for FSM-1
logic en_pipeline1,en_pipeline2,en_pipeline3,en_pipeline4; // Pipeline enable signals
logic en_pipeline5,en_pipeline6,en_pipeline7,en_pipeline8; // Pipeline enable signals
logic [13:0] ynout_in;
logic valid1_in;
logic [9:0] xt0_in,xt1_in,xt2_in,xt3_in;
logic [12:0] yt0_in,yt1_in,yt2_in,yt3_in;
logic [11:0] ffx0_in,ffx1_in,ffx2_in,ffx3_in;

// Pipeline Enables
assign en_pipeline1 = ENABLE;
assign en_pipeline7 = valid1;
assign en_pipeline8 = valid2;

assign input_1 = (ixx != 0);            // Input for FSM-1

// FSM-1 - Moore Machine with 8 states; S0,S1,S2,S3,S4,S5,S6,S7
h264coretransform_controller controller(
                            .CLK(CLK),
                            .RESET(RESET),
                            .ENABLE(ENABLE),
                            .input_1(input_1),
                            .en_pipeline2(en_pipeline2),
                            .en_pipeline3(en_pipeline3),
                            .en_pipeline4(en_pipeline4),
                            .en_pipeline5(en_pipeline5)
                            );

// ########################################

// ###### RESET, READY & COUNTERS #########

// ########################################
always_ff @(posedge CLK)
begin
    // Reset Signal is active low
    if (~RESET)
    begin
        ixx <= 0;   // Reset counter
    end
    else 
    begin
        if (ENABLE || (ixx != 0)) // Counter for ixx
        begin
            ixx <= ixx + 1;
        end
        if (en_pipeline6)         // Counter for iyn
        begin
            iyn <= iyn + 1;
        end
    end

    // READY Signal Generator
    if (ixx < 3 && (iyn >= 14 || iyn==0))
    begin
        READY <= 1;
    end
    else
    begin
        READY <= 0;
    end
end

// ########################################

// ######  Pipeline Register #1  ##########

// ########################################

always_comb
begin
    // --initial helpers (TT+1) (10bit from 9bit)
    xt0_in = {xx0[8], xx0} + {xx3[8], xx3};			//--xx0 + xx3
    xt1_in = {xx1[8], xx1} + {xx2[8], xx2};			//--xx1 + xx2
    xt2_in = {xx1[8], xx1} - {xx2[8], xx2};			//--xx1 - xx2
    xt3_in = {xx0[8], xx0} - {xx3[8], xx3};			//--xx0 - xx3
end

// Pipeline Register # 1    
always_ff @(posedge CLK)
begin
    if (ENABLE)
    begin
        // --initial helpers (TT+1) (10bit from 9bit)
        xt0 <= xt0_in;			//--xx0 + xx3
        xt1 <= xt1_in;			//--xx1 + xx2
        xt2 <= xt2_in;			//--xx1 - xx2
        xt3 <= xt3_in;			//--xx0 - xx3
    end
end

// ########################################

// ###### Pipeline Registers 2-5 ##########

// ########################################

always_comb
begin
    // --now compute row of FF matrix at TT+2 (12bit from 10bit)
    ffx0_in = {xt0[9], xt0[9], xt0} + {xt1[9], xt1[9], xt1};	    //--xt0 + xt1
    ffx1_in = {xt2[9], xt2[9], xt2} + {xt3[9], xt3, 1'b0};	 	//--xt2 + 2*xt3
    ffx2_in = {xt0[9], xt0[9], xt0} - {xt1[9], xt1[9], xt1};	    //--xt0 - xt1
    ffx3_in = {xt3[9], xt3[9], xt3} - {xt2[9], xt2, 1'b0};		//--xt3 - 2*xt2
end
// Pipeline Registers 2-5
always_ff @(posedge CLK)
begin
    // Registers powered by FSM-1
    // Pipeline 2
    if (en_pipeline2)
    begin
        // --now compute row of FF matrix at TT+2 (12bit from 10bit)
        ffx0 <= ffx0_in;
        ffx1 <= ffx1_in;
        ffx2 <= ffx2_in;
        ffx3 <= ffx3_in;
    end

    //--place rows 0,1,2 into slots at TT+3,4,5
    // Pipeline 3
    if (en_pipeline3) 
    begin
        ff00 <= ffx0;
        ff01 <= ffx1;
        ff02 <= ffx2;
        ff03 <= ffx3;
    end

    // Pipeline 4
    if (en_pipeline4)
    begin
        ff10 <= ffx0;
        ff11 <= ffx1;
        ff12 <= ffx2;
        ff13 <= ffx3;
    end 

    // Pipeline 5
    if (en_pipeline5) 
    begin
        ff20 <= ffx0;
        ff21 <= ffx1;
        ff22 <= ffx2;
        ff23 <= ffx3;
    end
end


// ########################################

// ######  Pipeline Register #6  ##########

// ########################################

// Muxes before Pipeline #6
always_comb
begin
    case(iyn)
        4'd15 : ynyx = {ROW0, COL0};
        4'd14 : ynyx = {ROW0, COL1};
        4'd13 : ynyx = {ROW1, COL0};
        4'd12 : ynyx = {ROW2, COL0};
        4'd11 : ynyx = {ROW1, COL1};
        4'd10 : ynyx = {ROW0, COL2};
        4'd9  : ynyx = {ROW0, COL3};
        4'd8  : ynyx = {ROW1, COL2};
        4'd7  : ynyx = {ROW2, COL1};
        4'd6  : ynyx = {ROW3, COL0};
        4'd5  : ynyx = {ROW3, COL1};
        4'd4  : ynyx = {ROW2, COL2};
        4'd3  : ynyx = {ROW1, COL3};
        4'd2  : ynyx = {ROW2, COL3};
        4'd1  : ynyx = {ROW3, COL2};
        default : ynyx = {ROW3, COL3};
    endcase

    //assign yny = ynyx[3:2];  -- Unconditionally assigned
    //assign ynx = ynyx [1:0]; -- Unconditionally assigned

    case(ynx)
        2'd0:
        begin
            ff0pu = ff00;
            ff1pu = ff10;
            ff2pu = ff20;
            ff3pu = ffx0;
        end

        2'd1:
        begin
            ff0pu = ff01;
            ff1pu = ff11;
            ff2pu = ff21;
            ff3pu = ffx1;
        end

        2'd2:
        begin
            ff0pu = ff02;
            ff1pu = ff12;
            ff2pu = ff22;
            ff3pu = ffx2;
        end

        default:
        begin
            ff0pu = ff03;
            ff1pu = ff13;
            ff2pu = ff23;
            ff3pu = ffx3;
        end
    endcase
end

// Pipeline #6 & Register below Pipeline #6
always_comb
begin
    // en_pipeline6 Signal Generator for pipeline # 06
    if ((ixx == 5) || (iyn != 0))
        en_pipeline6 = 1;
    else
        en_pipeline6 = 0;

    // Mux below pipeline # 06
    if (en_pipeline6)
        valid1_in = 1'b1;
    else
        valid1_in = 1'b0;
end

// Signals used in Pipeline #6 are generated above and in always_comb block
always_ff @(posedge CLK)
begin
    if (en_pipeline6)
    begin
        ff0p <= ff0pu;
        ff1p <= ff1pu;
        ff2p <= ff2pu;
        ff3p <= ff3pu;
        yny1 <= yny;
    end

    // valid1 Register below Pipeline # 6
    // CLK dependent
    valid1 <= valid1_in;   // en_pipeline7
end

// ########################################

// ######  Pipeline Register #7  ##########

// ########################################

always_comb
begin
    yt0_in = {ff0p[11], ff0p} + {ff3p[11], ff3p};	    //--ff0 + ff3
    yt1_in = {ff1p[11], ff1p} + {ff2p[11], ff2p};	    //--ff1 + ff2
    yt2_in = {ff1p[11], ff1p} - {ff2p[11], ff2p};	    //--ff1 - ff2
    yt3_in = {ff0p[11], ff0p} - {ff3p[11], ff3p};	    //--ff0 - ff3
end

// Pipeline 7
always_ff @(posedge CLK)
begin
    if (en_pipeline7) 
    begin
        yt0 <= yt0_in;
        yt1 <= yt1_in;
        yt2 <= yt2_in;
        yt3 <= yt3_in;
        yny2 <= yny1;
    end

    // Valid2
    valid2 <= valid1;   // en_pipeline8
end

// ########################################

// ######  Pipeline Register #8  ##########

// ########################################

// MUX before Pipeline # 08
always_comb
begin
    //--compute final YNOUT values (14bit from 13bit)
    // yny -> yny1 -> yny2 ('yny2' is 'yny' after delay of '2 clock cycles')
    if (yny2==0) 
    begin
        ynout_in = {yt0[12], yt0} + {yt1[12], yt1};	//-- yt0 + yt1
    end
    else if (yny2==1) 
    begin
        ynout_in = {yt2[12], yt2} + {yt3, 1'b0};		//-- yt2 + 2*yt3
    end
    else if (yny2==2) 
    begin
        ynout_in = {yt0[12], yt0} - {yt1[12], yt1};    //-- yt0 - yt1
    end	   
    else
    begin
        ynout_in = {yt3[12], yt3} - {yt2, 1'b0};	    //-- yt3 - 2*yt2
    end 
end
// Pipeline # 08 (ENDING)
always_ff @(posedge CLK)
begin
    // OUTPUT "ynout_in"is computed at the end of always_comb block

    if (en_pipeline8)
    begin
        YNOUT <= ynout_in;
    end

    // VALID
    VALID <= valid2;
end

endmodule

h264/updates/dctransform/cocotb/wrapper/h264coretransform_wrapper.sv
module h264coretransform_wrapper(
    // Variable/Signals Declaration
    input  logic CLK,
    input  logic [35:0] XXIN,
    input  logic RESET,
    input  logic ENABLE,
    output logic READY,
    output logic VALID,
    output logic [13:0] YNOUT
);


    // Call Module
    h264coretransform DUT(
        .CLK(CLK),
        .XXIN(XXIN),
        .RESET(RESET),
        .ENABLE(ENABLE),
        .READY(READY),
        .VALID(VALID),
        .YNOUT(YNOUT)
    );

initial
begin
    $dumpfile ("wave.vcd");
    $dumpvars;
end

endmodule

h264/updates/coretransform/cocotb/wave.vcd
$date
	Sat Sep  7 22:03:47 2024
$end
$version
	Icarus Verilog
$end
$timescale
	1ps
$end
$scope module h264coretransform_wrapper $end
$var wire 1 ! CLK $end
$var wire 1 " ENABLE $end
$var wire 1 # RESET $end
$var wire 36 $ XXIN [35:0] $end
$var wire 14 % YNOUT [13:0] $end
$var wire 1 & VALID $end
$var wire 1 ' READY $end
$scope module DUT $end
$var wire 1 ! CLK $end
$var wire 1 " ENABLE $end
$var wire 1 # RESET $end
$var wire 36 ( XXIN [35:0] $end
$var wire 1 ) en_pipeline1 $end
$var wire 1 * en_pipeline7 $end
$var wire 1 + en_pipeline8 $end
$var wire 2 , yny [1:0] $end
$var wire 2 - ynx [1:0] $end
$var wire 9 . xx3 [8:0] $end
$var wire 9 / xx2 [8:0] $end
$var wire 9 0 xx1 [8:0] $end
$var wire 9 1 xx0 [8:0] $end
$var wire 1 2 input_1 $end
$var wire 1 3 en_pipeline5 $end
$var wire 1 4 en_pipeline4 $end
$var wire 1 5 en_pipeline3 $end
$var wire 1 6 en_pipeline2 $end
$var reg 1 ' READY $end
$var reg 1 & VALID $end
$var reg 14 7 YNOUT [13:0] $end
$var reg 1 8 en_pipeline6 $end
$var reg 12 9 ff00 [11:0] $end
$var reg 12 : ff01 [11:0] $end
$var reg 12 ; ff02 [11:0] $end
$var reg 12 < ff03 [11:0] $end
$var reg 12 = ff0p [11:0] $end
$var reg 12 > ff0pu [11:0] $end
$var reg 12 ? ff10 [11:0] $end
$var reg 12 @ ff11 [11:0] $end
$var reg 12 A ff12 [11:0] $end
$var reg 12 B ff13 [11:0] $end
$var reg 12 C ff1p [11:0] $end
$var reg 12 D ff1pu [11:0] $end
$var reg 12 E ff20 [11:0] $end
$var reg 12 F ff21 [11:0] $end
$var reg 12 G ff22 [11:0] $end
$var reg 12 H ff23 [11:0] $end
$var reg 12 I ff2p [11:0] $end
$var reg 12 J ff2pu [11:0] $end
$var reg 12 K ff3p [11:0] $end
$var reg 12 L ff3pu [11:0] $end
$var reg 12 M ffx0 [11:0] $end
$var reg 12 N ffx0_in [11:0] $end
$var reg 12 O ffx1 [11:0] $end
$var reg 12 P ffx1_in [11:0] $end
$var reg 12 Q ffx2 [11:0] $end
$var reg 12 R ffx2_in [11:0] $end
$var reg 12 S ffx3 [11:0] $end
$var reg 12 T ffx3_in [11:0] $end
$var reg 3 U ixx [2:0] $end
$var reg 4 V iyn [3:0] $end
$var reg 1 W valid1 $end
$var reg 1 X valid1_in $end
$var reg 1 Y valid2 $end
$var reg 10 Z xt0 [9:0] $end
$var reg 10 [ xt0_in [9:0] $end
$var reg 10 \ xt1 [9:0] $end
$var reg 10 ] xt1_in [9:0] $end
$var reg 10 ^ xt2 [9:0] $end
$var reg 10 _ xt2_in [9:0] $end
$var reg 10 ` xt3 [9:0] $end
$var reg 10 a xt3_in [9:0] $end
$var reg 14 b ynout_in [13:0] $end
$var reg 2 c yny1 [1:0] $end
$var reg 2 d yny2 [1:0] $end
$var reg 4 e ynyx [3:0] $end
$var reg 13 f yt0 [12:0] $end
$var reg 13 g yt0_in [12:0] $end
$var reg 13 h yt1 [12:0] $end
$var reg 13 i yt1_in [12:0] $end
$var reg 13 j yt2 [12:0] $end
$var reg 13 k yt2_in [12:0] $end
$var reg 13 l yt3 [12:0] $end
$var reg 13 m yt3_in [12:0] $end
$scope module controller $end
$var wire 1 ! CLK $end
$var wire 1 " ENABLE $end
$var wire 1 # RESET $end
$var wire 1 2 input_1 $end
$var reg 3 n c_state1 [2:0] $end
$var reg 1 6 en_pipeline2 $end
$var reg 1 5 en_pipeline3 $end
$var reg 1 4 en_pipeline4 $end
$var reg 1 3 en_pipeline5 $end
$var reg 3 o n_state1 [2:0] $end
$upscope $end
$upscope $end
$upscope $end
$enddefinitions $end
#0
$dumpvars
b0 o
bx n
bx m
b0 l
bx k
b0 j
bx i
b0 h
bx g
b0 f
b0 e
b0 d
b0 c
bx b
bx a
b0 `
bx _
b0 ^
bx ]
b0 \
bx [
b0 Z
0Y
xX
0W
b0 V
b0 U
bx T
b0 S
bx R
b0 Q
bx P
b0 O
bx N
b0 M
b0 L
b0 K
b0 J
b0 I
b0 H
b0 G
b0 F
b0 E
b0 D
b0 C
b0 B
b0 A
b0 @
b0 ?
b0 >
b0 =
b0 <
b0 ;
b0 :
b0 9
x8
b0 7
06
05
04
03
02
bz 1
bz 0
bz /
bz .
b0 -
b0 ,
0+
0*
z)
bz (
0'
0&
b0 %
bz $
z#
z"
0!
$end
#10000
0)
0"
0#
b0 n
1'
x*
xW
1!
#20000
0!
#30000
x+
xY
1!
#40000
0!
#50000
b10 a
b0 _
b101001100 ]
b101011000 [
b10101101 1
b10100110 0
b10100110 /
b10101011 .
b1 o
b10101011010100110010100110010101101 $
b10101011010100110010100110010101101 (
1)
1"
1#
x&
1!
#60000
0!
#70000
b1111111111 a
b1111111111 _
b101010001 ]
b101010101 [
b10101010 1
b10101000 0
b10101001 /
b10101011010101001010101000010101010 $
b10101011010101001010101000010101010 (
b10 T
b1100 R
b100 P
b1010100100 N
0X
08
16
b10 o
b10 `
b101001100 \
b101011000 Z
12
b1 U
b1 n
1!
#80000
0!
#90000
b1111110111 a
b1111111100 _
b101001010 ]
b101001001 [
b10100000 1
b10100011 0
b10100111 /
b10101001 .
b10101001010100111010100011010100000 $
b10101001010100111010100011010100000 (
b11 ,
b11 -
15
b11 o
b1 T
b100 R
b111111111101 P
b1010100110 N
b10 L
b1111 e
b10 n
b10 U
b1111111111 `
b1111111111 ^
b101010001 \
b101010101 Z
b10 S
b1100 Q
b100 O
b1010100100 M
0*
0W
1!
#100000
0!
#110000
b1111111100 a
b1111111110 _
b101001110 ]
b101001000 [
b10100010 1
b10100110 0
b10101000 /
b10100110 .
b10100110010101000010100110010100010 $
b10100110010101000010100110010100010 (
b1 L
b10 >
b111111111111 T
b111111111111 R
b111111101010 P
b1010010011 N
14
05
b100 o
0+
0Y
b10 <
b1100 ;
b100 :
b1010100100 9
b1 S
b100 Q
b111111111101 O
b1010100110 M
b1111110111 `
b1111111100 ^
b101001010 \
b101001001 Z
b11 U
b11 n
1!
#120000
0!
#130000
0)
0"
13
04
b101 o
b0 T
b111111111010 R
b111111110110 P
b1010010110 N
b111111111111 L
b1 D
b100 n
0'
b100 U
b1111111100 `
b1111111110 ^
b101001110 \
b101001000 Z
b1 B
b100 A
b111111111101 @
b1010100110 ?
b111111111111 S
b111111111111 Q
b111111101010 O
b1010010011 M
0&
1!
#140000
0!
#150000
b0 L
b111111111111 J
1X
18
03
06
b110 o
b111111111111 H
b111111111111 G
b111111101010 F
b1010010011 E
b0 S
b111111111010 Q
b111111110110 O
b1010010110 M
b101 U
b101 n
1!
#160000
0!
#170000
b111111111010 L
b100 D
b1100 >
b10 -
b111 o
b1110 e
b10 m
b10 k
b0 i
b10 g
b110 n
b1 V
b110 U
1*
1W
b11 c
b111111111111 I
b1 C
b10 =
1!
#180000
0!
#190000
b0 L
b1 D
b10 >
b10 ,
b11 -
b11111111111110 b
b10010 m
b101 k
b11 i
b110 g
b1011 e
b0 o
1+
1Y
b11 d
b10 l
b10 j
b10 f
b111111111010 K
b100 C
b1100 =
b10 V
b111 U
b111 n
1!
#200000
0!
#210000
b1 ,
b111 e
b10 m
b10 k
b0 i
b10 g
b1000 b
b0 n
b11 V
02
b0 U
b10 c
b0 K
b1 C
b10 =
b10010 l
b101 j
b11 h
b110 f
1&
b11111111111110 %
b11111111111110 7
1!
#220000
0!
#230000
b111111111010 L
b100 D
b1100 >
b10 ,
b10 -
b10 b
b1010 e
b1000 %
b1000 7
b10 d
b10 l
b10 j
b0 h
b10 f
b1 c
b100 V
1!
